src/mux.v
// 2-to-1 Multiplexer (16-bit)
// Owner: Neeraj Arde

module mux2to1( //module declaration (simplest is mux which basically uses a select signal to choose between two inputs)
    input  [15:0] in0,    // Input 0 (which is 16 bits wide)
    input  [15:0] in1,    // Input 1 (also a 16 bit wide)
    input         sel,    // Select signal (this is a control signal)
    output [15:0] out     // Output (also a 16 bit wide, whatever input is selected by sel will be assigned to out)
);

    assign out = sel ? in1 : in0; // if sel -> 1, out = in1 , else if sel ->0 out = in0

endmodule

src/data_memory.v
// Data Memory
// Byte-addressed, 256 bytes, big-endian word access
// Owner: Prasanna Sairam Govindarajulu

module data_memory(clk, MemRead, MemWrite, addr, write_data, read_data);

input clk;
input MemRead;
input MemWrite;
input [15:0] addr;
input [15:0] write_data;
output [15:0] read_data;

/* Safe byte indices: always in [0:255] (second byte uses base when base==255) */
wire [7:0] base_idx = addr[7:0];
wire [8:0] byte_sum = {1'b0, base_idx} + 9'd1;
wire [7:0] hi_idx   = byte_sum[8] ? base_idx : byte_sum[7:0];

/* 256-byte data memory */
reg [7:0] mem [0:255];
integer i;

/* initialize memory to 0 */
initial begin
    for (i = 0; i < 256; i = i + 1)
        mem[i] = 8'b0;
end

/* big-endian 16-bit read:
   high byte at mem[addr], low byte at mem[addr+1] */
assign read_data = MemRead ? {mem[base_idx], mem[hi_idx]} : 16'b0;

/* write on rising edge of clock */
always @(posedge clk) begin
    if (MemWrite) begin
        mem[base_idx] <= write_data[15:8];
        mem[hi_idx]   <= write_data[7:0];
    end
end

endmodule

src/alu.v
// ALU Module
// Supports: add, sub, sll, and (R-type), addi (I-type)
// Owner: Neeraj Arde

module alu( //declaration of ALU module : takes two 16 bit inputs, one 4 bit control signal and produces a 16 bit output and a zero flag
// ALU performs arithmetic, logic, shift, and comparison operations
// Control signal selects which operation to execute
    input  [15:0] A,        // First operand (R[rs])
    input  [15:0] B,        // Second operand (R[rt/rd] or sign-extended immediate)
    input  [3:0]  ALUCtrl,  // ALU control signal
    output reg [15:0] Result,
    output  Zero      // Zero flag (used by beq/bne)
);
    // we will use these following alu control codes to determine which operation to perform
    // ALU Control Codes
    // 0000 = add
    // 0001 = sub
    // 0010 = sll
    // 0011 = and

    always @(*) begin
        case (ALUCtrl)
        //binary notation : 4'b0000 means 4 bit binary number with value 0000
            4'b0000: Result = A + B;          // add / addi / lw/sw (since lw/sw also uses add to calculate address)
            4'b0001: Result = A - B;          // sub / beq/bne (since beq/bne also uses sub to compare values)
            4'b0010: Result = B << A;         // sll: shift R[rt/rd] by R[rs] bits
            4'b0011: Result = A & B;          // and
            default: Result = 16'b0;
        endcase
    end

     assign Zero = (Result == 16'b0); // zero flag is set if the result of ALU operation is zero, i.e. 1 if zero , else 0 if result is not zero

endmodule

src/sign_extend_12.v
// Sign Extension Module for Jump (12-bit address)
// Extends 12-bit address to 16-bit signed integer
// Owner: Neeraj Arde

module sign_extend_12( //module declaration for sign extension for jump instruction, takes a 12 bit input and produces a 16 bit output
    input  [11:0] addr_in,   // 12-bit jump address as an input
    output [15:0] addr_out   // 16-bit sign-extended output
);

    assign addr_out = {{4{addr_in[11]}}, addr_in}; // sign extension logic basically takes the msb and extends it 4 times and concatenates it with the original input to produce the output

endmodule

src/sign_extend_4.v
// Sign Extension Module
// Extends 4-bit immediate to 16-bit signed integer
// Owner: Neeraj Arde

module sign_extend( // module declaration for sign extension, takes a 4 bit input and produces a 16 bit output
    input  [3:0]  imm_in,    // 4-bit immediate from instruction
    output [15:0] imm_out    // 16-bit sign-extended output
);

    assign imm_out = {{12{imm_in[3]}}, imm_in}; // sign extension: i.e. to just extend the msb of the input 12 times and concatenate it with the original input 

endmodule

src/instruction_memory.v
// Instruction memory
// 256 bytes total = 128 instructions
// PC gives a byte address
// Each instruction is 16 bits, so two bytes are read at a time

module instruction_memory(addr, instruction);

input [15:0] addr;
output [15:0] instruction;

/* Safe byte indices: always in [0:255] (second byte uses base when base==255) */
wire [7:0] base_idx = addr[7:0];
wire [8:0] byte_sum = {1'b0, base_idx} + 9'd1;
wire [7:0] hi_idx   = byte_sum[8] ? base_idx : byte_sum[7:0];

/* 256-byte instruction memory */
reg [7:0] mem [0:255];
integer i;

/* instruction stored in two bytes */
assign instruction = {mem[base_idx], mem[hi_idx]};

initial begin
    /* clear memory */
    for (i = 0; i < 256; i = i + 1)
        mem[i] = 8'b0;

    /* sample program */

    /* addi $s1, $s0, 5 */
    mem[0]  = 8'h31;
    mem[1]  = 8'h05;

    /* addi $s2, $s0, 3 */
    mem[2]  = 8'h32;
    mem[3]  = 8'h03;

    /* add */
    mem[4]  = 8'h01;
    mem[5]  = 8'h20;

    /* sub */
    mem[6]  = 8'h01;
    mem[7]  = 8'h21;

    /* and */
    mem[8]  = 8'h01;
    mem[9]  = 8'h23;

    /* sll */
    mem[10] = 8'h01;
    mem[11] = 8'h22;

    /* sw */
    mem[12] = 8'h21;
    mem[13] = 8'h00;

    /* lw */
    mem[14] = 8'h17;
    mem[15] = 8'h00;

    /* beq */
    mem[16] = 8'h47;
    mem[17] = 8'h11;

    /* addi $s0, $s0, 1 */
    mem[18] = 8'h30;
    mem[19] = 8'h01;

    /* jump */
    mem[20] = 8'h6F;
    mem[21] = 8'hF5;
end

endmodule

src/program_counter.v
module program_counter(
    input clock,
    input resetProc,
    input  [15:0] pcNext,  
    output reg [15:0] pc     
);
    always @(posedge clock or posedge resetProc) begin
        if (resetProc == 1)
            pc <= 0;
        else
            pc <= pcNext;
    end
endmodule

src/register_file.v
module register_file(
    input         clock,
    input         registerWrite,    
    input  [3:0]  rs,          
    input  [3:0]  rtrd,       
    input  [15:0] writeData,  
    output [15:0] readData1,  
    output [15:0] readData2   
);
    integer i; // declaring i for the loop
    reg [15:0] registers [0:15]; // declaring an array of 16 regs, each being 16 bitswide

    initial begin // from the slides 
    for (i = 0; i < 16; i = i + 1) begin
        registers[i] = 16'b0;
    end //looping to set all registers to 0 at the start
    end

    assign readData1 = registers[rtrd];   
    assign readData2 = registers[rs];
    always @(posedge clock) begin // when rising edge of the clock -> we check the regwrite signal
        if (registerWrite == 1) begin //if regwrite is true, we write data to the reg file at the index 
            registers[rtrd] <= writeData;
        end 
    end
endmodule

src/control_unit.v
module control_unit(
    input  [3:0] opcode,       // this gets the opcode for the instruction type
    input  [3:0] funct,        // func for distinguishing r-type instr
    output reg       RegWrite, // signal to indicate write to reg
    output reg       ALUSrc,   // alusrc decides if the second operand is immediate or not
    output reg       MemRead,  // indicates read from mem
    output reg       MemWrite, //indicares write to mem
    output reg       MemToReg, // if data is written to reg from mem
    output reg       Branch,   // in case of branch
    output reg       BranchNE, // branch not equal
    output reg       Jump,     // in case of jump
    output reg [3:0] ALUCtrl   // fir ALU operations (+, - etc.)
);

    //the op and func codes are fixed as per the document
    parameter opcodeR =0;
    parameter opcodeLW = 1;
    parameter opcodeSW = 2;
    parameter opcodeI = 3;
    parameter opcodeBEQ =4;
    parameter opcodeBNE = 5;
    parameter opcodeJMP =6;

    // func codes (ONLY for r-type)
    parameter fnAdd = 0;
    parameter fnSub = 1;
    parameter fnSll =2;
    parameter fnAnd = 3;

    //aluctrl cide for alu operatuins
    parameter aluAdd =0;
    parameter aluSub =1;
    parameter aluSll = 2;
    parameter aluAnd =  3;

    always @(*) begin //setting all signals to 0 (default)
        RegWrite = 0;
        ALUSrc   = 0;
        MemRead  = 0;
        MemWrite = 0;
        MemToReg = 0;
        Branch   = 0;
        BranchNE = 0;
        Jump     = 0;
        ALUCtrl  = aluAdd;

        case (opcode)
            opcodeR: begin
                RegWrite = 1;
                case (funct)
                    fnAdd: ALUCtrl = aluAdd;
                    fnSub: ALUCtrl = aluSub;
                    fnSll: ALUCtrl = aluSll;
                    fnAnd: ALUCtrl = aluAnd;
                    default: ALUCtrl = aluAdd;
                endcase
            end

            opcodeLW: begin
                RegWrite = 1;
                ALUSrc   = 1;
                MemRead  = 1;
                MemToReg = 1;
                ALUCtrl  = aluAdd;
            end

            opcodeSW: begin
                ALUSrc   = 1;
                MemWrite = 1;
                ALUCtrl  = aluAdd;
            end

            opcodeI: begin
                RegWrite = 1;
                ALUSrc   = 1;
                ALUCtrl  = aluAdd;
            end

            opcodeBEQ: begin
                Branch   = 1;
                ALUCtrl  = aluSub; //alu is sent the sub signal for comparision
            end

            
            opcodeBNE: begin
                RegWrite = 0;
                ALUSrc   = 0;
                Branch   = 1;
                BranchNE = 1;
                ALUCtrl  = aluSub;
            end

            opcodeJMP: begin
                Jump = 1;
            end


            default: begin
                //if no opcode is matched, nothing happens
            end
        endcase
    end

endmodule

src/processor.v
module processor_top( // declaration of processor module which will instantiate all the components of the processor and connect them
    input clk, 
    input reset 
);

    wire [15:0] instruction; //15:0 means 16 bits, wire declaration to hold the current insturction
    wire [15:0] pc_current; //current val of the program counter
    wire [15:0] pc_next; // next val of program counter

    wire [3:0] opcode = instruction[15:12]; //opcode the top 4 bits of the instruction
    wire [3:0] rs     = instruction[7:4]; //the source reg1ister, bits 7:4 of the instruction
    wire [3:0] rtrd   = instruction[11:8]; //the destination reg1ister, bits 11:8 of the instruction
    wire [3:0] imm4   = instruction[3:0]; //the immediate value, bits 3:0 of the instruction

    wire [15:0] imm_ext; //sign extended immediate value
    wire [15:0] alu_result; // result from the ALU operation
    wire [15:0] alu_in_b; //second input to the alu, either the val frm reg1ister or the sign extended immediate
    wire [15:0] mem_read_data;
    

    wire [15:0] reg1; //holds the value from source register
    wire [15:0] reg2; //holds the value frm destination register
    wire [15:0] wbdata;
    wire RegWrite, ALUSrc, MemRead, MemWrite, MemToReg, Branch, BranchNE, Jump;
    wire [3:0] ALUCtrl;
    wire zero;
    wire branchDecision;

    wire [15:0] pcplus2;
    wire [15:0] branchTarget;
    wire [15:0] jumpTarget;
    wire [15:0] PCBranchTarget;
    wire [15:0] jumpsignExt;
    wire [11:0] jumpAddr = instruction[11:0];
    wire [3:0]  funct = instruction[3:0];

    assign pcplus2       = pc_current + 2;
    assign branchTarget  = pcplus2 + (imm_ext << 1); // here we are calculating branchTaken
                                                      //address by adding sign extnd imm to pc+2
    assign jumpTarget    = pcplus2 + (jumpsignExt << 1); //same but for jump
    assign branchDecision = Branch & ((~BranchNE & zero) | (BranchNE & ~zero)); // we are basically calculating
                                                                                // whether branch will be taken or not based on the zero flag and branch signals



    control_unit cntrlunt ( //takes opcode (+funct if needed ) and generates control signal
    .opcode(opcode),
    .funct(funct),
    .RegWrite(RegWrite),
    .ALUSrc(ALUSrc),
    .MemRead(MemRead),
    .MemWrite(MemWrite),
    .MemToReg(MemToReg),
    .Branch(Branch),
    .BranchNE(BranchNE),
    .Jump(Jump),
    .ALUCtrl(ALUCtrl)
    );

    register_file regfile (
    .clock(clk),
    .registerWrite(RegWrite),
    .rs(rs),
    .rtrd(rtrd),
    .writeData(wbdata),
    .readData1(reg1),
    .readData2(reg2)
    );

    

    program_counter pc ( //module declaration for program counter
        .clock(clk),
        .resetProc(reset),
        .pcNext(pc_next),
        .pc(pc_current)
    );

    instruction_memory imem ( //module declaration for instruction memory
        .addr(pc_current),
        .instruction(instruction)
    );

    sign_extend se ( //module declaration for sign extension for immediate value
        .imm_in(imm4),
        .imm_out(imm_ext)
    );

    sign_extend_12 se_jump ( // used for jump addr calculation
    .addr_in(jumpAddr),
    .addr_out(jumpsignExt)
    );

    mux2to1 alu_mux ( //module declaration for mux to select between reg value and immediate value for second input to ALU
        .in0(reg1),
        .in1(imm_ext),
        .sel(ALUSrc),
        .out(alu_in_b)
    );

    alu alu_unit ( // module declaration for ALU, takes the opcode as control signal to determine the operation to perform on the inputs
        .A(reg2),
        .B(alu_in_b),
        .ALUCtrl(ALUCtrl),
        .Result(alu_result),
        .Zero(zero)
    );

    data_memory dmem (
        .clk(clk),
        .MemRead(MemRead),
        .MemWrite(MemWrite),
        .addr(alu_result),
        .write_data(reg1),
        .read_data(mem_read_data)
    );

    mux2to1 wbmux (
    .in0(alu_result),
    .in1(mem_read_data),
    .sel(MemToReg),
    .out(wbdata)
    );

    mux2to1 branchmux (
    .in0(pcplus2),
    .in1(branchTarget),
    .sel(branchDecision),
    .out(PCBranchTarget)
);

    mux2to1 jumpmux (
    .in0(PCBranchTarget),
    .in1(jumpTarget),
    .sel(Jump),
    .out(pc_next)
    );
endmodule

testbench/processor_tb.v
// Testbench for processor_top in processor.v only (hierarchical refs match that file)
`timescale 1ns / 1ps

module processor_tb;

    reg clk;
    reg reset;

    processor_top uut (
        .clk(clk),
        .reset(reset)
    );

    // Clock: half-period 5 time units
    initial clk = 1'b0;
    initial forever #5 clk = ~clk;

    initial begin
        $dumpfile("processor.vcd");
        $dumpvars(0, processor_tb);

        reset = 1'b1;
        #10 reset = 1'b0;

        // Signals: see wires in processor.v (wbdata = register file write data)
        $monitor(
            "t=%0t | PC=%04h | INSTR=%04h | ALU=%04h | DMEM_RD=%04h | RF_WD=%04h",
            $time,
            uut.pc_current,
            uut.instruction,
            uut.alu_result,
            uut.mem_read_data,
            uut.wbdata
        );

        #450;
        $display("Done at t=%0t", $time);
        $finish;
    end

endmodule

processor.vcd
$date
	Wed Apr  1 14:43:42 2026
$end
$version
	Icarus Verilog
$end
$timescale
	1ps
$end
$scope module processor_tb $end
$var reg 1 ! clk $end
$var reg 1 " reset $end
$scope module uut $end
$var wire 1 # branchDecision $end
$var wire 1 ! clk $end
$var wire 1 " reset $end
$var wire 1 $ zero $end
$var wire 16 % wbdata [15:0] $end
$var wire 4 & rtrd [3:0] $end
$var wire 4 ' rs [3:0] $end
$var wire 16 ( reg2 [15:0] $end
$var wire 16 ) reg1 [15:0] $end
$var wire 16 * pcplus2 [15:0] $end
$var wire 16 + pc_next [15:0] $end
$var wire 16 , pc_current [15:0] $end
$var wire 4 - opcode [3:0] $end
$var wire 16 . mem_read_data [15:0] $end
$var wire 16 / jumpsignExt [15:0] $end
$var wire 16 0 jumpTarget [15:0] $end
$var wire 12 1 jumpAddr [11:0] $end
$var wire 16 2 instruction [15:0] $end
$var wire 16 3 imm_ext [15:0] $end
$var wire 4 4 imm4 [3:0] $end
$var wire 4 5 funct [3:0] $end
$var wire 16 6 branchTarget [15:0] $end
$var wire 16 7 alu_result [15:0] $end
$var wire 16 8 alu_in_b [15:0] $end
$var wire 1 9 RegWrite $end
$var wire 16 : PCBranchTarget [15:0] $end
$var wire 1 ; MemWrite $end
$var wire 1 < MemToReg $end
$var wire 1 = MemRead $end
$var wire 1 > Jump $end
$var wire 1 ? BranchNE $end
$var wire 1 @ Branch $end
$var wire 1 A ALUSrc $end
$var wire 4 B ALUCtrl [3:0] $end
$scope module alu_mux $end
$var wire 1 A sel $end
$var wire 16 C out [15:0] $end
$var wire 16 D in1 [15:0] $end
$var wire 16 E in0 [15:0] $end
$upscope $end
$scope module alu_unit $end
$var wire 16 F B [15:0] $end
$var wire 1 $ Zero $end
$var wire 4 G ALUCtrl [3:0] $end
$var wire 16 H A [15:0] $end
$var reg 16 I Result [15:0] $end
$upscope $end
$scope module branchmux $end
$var wire 16 J in0 [15:0] $end
$var wire 16 K in1 [15:0] $end
$var wire 1 # sel $end
$var wire 16 L out [15:0] $end
$upscope $end
$scope module cntrlunt $end
$var wire 4 M funct [3:0] $end
$var wire 4 N opcode [3:0] $end
$var parameter 32 O aluAdd $end
$var parameter 32 P aluAnd $end
$var parameter 32 Q aluSll $end
$var parameter 32 R aluSub $end
$var parameter 32 S fnAdd $end
$var parameter 32 T fnAnd $end
$var parameter 32 U fnSll $end
$var parameter 32 V fnSub $end
$var parameter 32 W opcodeBEQ $end
$var parameter 32 X opcodeBNE $end
$var parameter 32 Y opcodeI $end
$var parameter 32 Z opcodeJMP $end
$var parameter 32 [ opcodeLW $end
$var parameter 32 \ opcodeR $end
$var parameter 32 ] opcodeSW $end
$var reg 4 ^ ALUCtrl [3:0] $end
$var reg 1 A ALUSrc $end
$var reg 1 @ Branch $end
$var reg 1 ? BranchNE $end
$var reg 1 > Jump $end
$var reg 1 = MemRead $end
$var reg 1 < MemToReg $end
$var reg 1 ; MemWrite $end
$var reg 1 9 RegWrite $end
$upscope $end
$scope module dmem $end
$var wire 1 = MemRead $end
$var wire 1 ; MemWrite $end
$var wire 16 _ addr [15:0] $end
$var wire 1 ! clk $end
$var wire 16 ` write_data [15:0] $end
$var wire 16 a read_data [15:0] $end
$var wire 8 b hi_idx [7:0] $end
$var wire 9 c byte_sum [8:0] $end
$var wire 8 d base_idx [7:0] $end
$var integer 32 e i [31:0] $end
$upscope $end
$scope module imem $end
$var wire 16 f instruction [15:0] $end
$var wire 8 g hi_idx [7:0] $end
$var wire 9 h byte_sum [8:0] $end
$var wire 8 i base_idx [7:0] $end
$var wire 16 j addr [15:0] $end
$var integer 32 k i [31:0] $end
$upscope $end
$scope module jumpmux $end
$var wire 16 l in0 [15:0] $end
$var wire 16 m in1 [15:0] $end
$var wire 1 > sel $end
$var wire 16 n out [15:0] $end
$upscope $end
$scope module pc $end
$var wire 1 ! clock $end
$var wire 16 o pcNext [15:0] $end
$var wire 1 " resetProc $end
$var reg 16 p pc [15:0] $end
$upscope $end
$scope module regfile $end
$var wire 1 ! clock $end
$var wire 16 q readData1 [15:0] $end
$var wire 16 r readData2 [15:0] $end
$var wire 1 9 registerWrite $end
$var wire 4 s rs [3:0] $end
$var wire 4 t rtrd [3:0] $end
$var wire 16 u writeData [15:0] $end
$var integer 32 v i [31:0] $end
$upscope $end
$scope module se $end
$var wire 4 w imm_in [3:0] $end
$var wire 16 x imm_out [15:0] $end
$upscope $end
$scope module se_jump $end
$var wire 12 y addr_in [11:0] $end
$var wire 16 z addr_out [15:0] $end
$upscope $end
$scope module wbmux $end
$var wire 16 { in0 [15:0] $end
$var wire 16 | in1 [15:0] $end
$var wire 1 < sel $end
$var wire 16 } out [15:0] $end
$upscope $end
$upscope $end
$upscope $end
$enddefinitions $end
$comment Show the parameter values. $end
$dumpall
b10 ]
b0 \
b1 [
b110 Z
b11 Y
b101 X
b100 W
b1 V
b10 U
b11 T
b0 S
b1 R
b10 Q
b11 P
b0 O
$end
#0
$dumpvars
b101 }
b0 |
b101 {
b100000101 z
b100000101 y
b101 x
b101 w
b10000 v
b101 u
b1 t
b0 s
b0 r
b0 q
b0 p
b10 o
b10 n
b1000001100 m
b10 l
b100000000 k
b0 j
b0 i
b1 h
b1 g
b11000100000101 f
b100000000 e
b101 d
b110 c
b110 b
b0 a
b0 `
b101 _
b0 ^
b11 N
b101 M
b10 L
b1100 K
b10 J
b101 I
b0 H
b0 G
b101 F
b0 E
b101 D
b101 C
b0 B
1A
0@
0?
0>
0=
0<
0;
b10 :
19
b101 8
b101 7
b1100 6
b101 5
b101 4
b101 3
b11000100000101 2
b100000101 1
b1000001100 0
b100000101 /
b0 .
b11 -
b0 ,
b10 +
b10 *
b0 )
b0 (
b0 '
b1 &
b101 %
0$
0#
1"
0!
$end
#5000
b101 )
b101 E
b101 `
b101 q
1!
#10000
0!
0"
#15000
b100 b
b100 c
b11 d
b11 %
b11 u
b11 }
b11 7
b11 I
b11 _
b11 {
b11 8
b11 C
b11 F
1A
19
b11 3
b11 D
b11 x
b11 5
b11 M
b11 4
b11 w
b1000000011 /
b1000000011 z
b0 )
b0 E
b0 `
b0 q
b11 g
b1000000011 1
b1000000011 y
b10 &
b10 t
b11001000000011 2
b11001000000011 f
b11 h
b100 +
b100 n
b100 o
b10 i
b100 :
b100 L
b100 l
b1010 6
b1010 K
b10000001010 0
b10000001010 m
b100 *
b100 J
b10 ,
b10 j
b10 p
1!
#20000
0!
#25000
b1001 b
b0 3
b0 D
b0 x
b11 (
b11 H
b11 r
b1001 c
b0 5
b0 M
b0 4
b0 w
b10 '
b10 s
b1000 d
b1000 %
b1000 u
b1000 }
0$
b1000 7
b1000 I
b1000 _
b1000 {
b101 8
b101 C
b101 F
b100100000 /
b100100000 z
b0 B
b0 G
b0 ^
0A
19
b101 g
b100100000 1
b100100000 y
b1 &
b1 t
b0 -
b0 N
b100100000 2
b100100000 f
b101 h
b110 +
b110 n
b110 o
b100 i
b110 :
b110 L
b110 l
b101 )
b101 E
b101 `
b101 q
b110 6
b110 K
b1001000110 0
b1001000110 m
b110 *
b110 J
b100 ,
b100 j
b100 p
1!
#30000
0!
#35000
b1 B
b1 G
b1 ^
19
b100100001 /
b100100001 z
b1 3
b1 D
b1 x
b1 5
b1 M
b100100001 1
b100100001 y
b1 4
b1 w
b11111100 b
b100100001 2
b100100001 f
b11111100 c
b111 g
b11111011 d
b1111111111111011 %
b1111111111111011 u
b1111111111111011 }
b1111111111111011 7
b1111111111111011 I
b1111111111111011 _
b1111111111111011 {
b111 h
b1000 +
b1000 n
b1000 o
b1000 8
b1000 C
b1000 F
b110 i
b1000 :
b1000 L
b1000 l
b1000 )
b1000 E
b1000 `
b1000 q
b1010 6
b1010 K
b1001001010 0
b1001001010 m
b1000 *
b1000 J
b110 ,
b110 j
b110 p
1!
#40000
0!
#45000
b11 B
b11 G
b11 ^
19
b100100011 /
b100100011 z
b11 3
b11 D
b11 x
b11 5
b11 M
b100100011 1
b100100011 y
b11 4
b11 w
b100 b
b100100011 2
b100100011 f
b100 c
b1001 g
b11 d
b11 %
b11 u
b11 }
b11 7
b11 I
b11 _
b11 {
b1001 h
b1010 +
b1010 n
b1010 o
b1111111111111011 8
b1111111111111011 C
b1111111111111011 F
b1000 i
b1010 :
b1010 L
b1010 l
b1111111111111011 )
b1111111111111011 E
b1111111111111011 `
b1111111111111011 q
b10000 6
b10000 K
b1001010000 0
b1001010000 m
b1010 *
b1010 J
b1000 ,
b1000 j
b1000 p
1!
#50000
0!
#55000
b11001 b
b11001 c
b11000 d
b11000 %
b11000 u
b11000 }
b11000 7
b11000 I
b11000 _
b11000 {
b10 B
b10 G
b10 ^
19
b100100010 /
b100100010 z
b10 3
b10 D
b10 x
b10 5
b10 M
b100100010 1
b100100010 y
b10 4
b10 w
b100100010 2
b100100010 f
b1011 g
b1011 h
b1100 +
b1100 n
b1100 o
b11 8
b11 C
b11 F
b1010 i
b1100 :
b1100 L
b1100 l
b11 )
b11 E
b11 `
b11 q
b10000 6
b10000 K
b1001010000 0
b1001010000 m
b1100 *
b1100 J
b1010 ,
b1010 j
b1010 p
1!
#60000
0!
#65000
1$
b100000000 /
b100000000 z
b0 3
b0 D
b0 x
b0 (
b0 H
b0 r
b0 5
b0 M
b100000000 1
b100000000 y
b0 4
b0 w
b0 '
b0 s
b1 b
1;
1A
b0 B
b0 G
b0 ^
09
b1 c
b1101 g
b10 -
b10 N
b0 d
b0 %
b0 u
b0 }
b10000100000000 2
b10000100000000 f
b0 7
b0 I
b0 _
b0 {
b1101 h
b1110 +
b1110 n
b1110 o
b0 8
b0 C
b0 F
b1100 i
b1110 :
b1110 L
b1110 l
b11000 )
b11000 E
b11000 `
b11000 q
b1110 6
b1110 K
b1000001110 0
b1000001110 m
b1110 *
b1110 J
b1100 ,
b1100 j
b1100 p
1!
#70000
0!
#75000
b11000 %
b11000 u
b11000 }
b11000 .
b11000 a
b11000 |
b11100000000 /
b11100000000 z
b0 )
b0 E
b0 `
b0 q
1<
1=
19
0;
1A
b1111 g
b11100000000 1
b11100000000 y
b111 &
b111 t
b1 -
b1 N
b1011100000000 2
b1011100000000 f
b1111 h
b10000 +
b10000 n
b10000 o
b1110 i
b10000 :
b10000 L
b10000 l
b10000 6
b10000 K
b111000010000 0
b111000010000 m
b10000 *
b10000 J
b1110 ,
b1110 j
b1110 p
1!
#80000
0!
#85000
b1 b
b11100010001 /
b11100010001 z
b1 3
b1 D
b1 x
b11000 (
b11000 H
b11000 r
b1 c
b1 5
b1 M
b11100010001 1
b11100010001 y
b1 4
b1 w
b1 '
b1 s
b0 d
1$
b0 7
b0 I
b0 _
b0 {
1#
b0 %
b0 u
b0 }
b0 .
b0 a
b0 |
b11000 8
b11000 C
b11000 F
b1 B
b1 G
b1 ^
1@
0<
0=
0A
09
b10001 g
b100 -
b100 N
b100011100010001 2
b100011100010001 f
b10001 h
b10100 +
b10100 n
b10100 o
b10000 i
b10100 :
b10100 L
b10100 l
b11000 )
b11000 E
b11000 `
b11000 q
b10100 6
b10100 K
b111000110100 0
b111000110100 m
b10010 *
b10010 J
b10000 ,
b10000 j
b10000 p
1!
#90000
0!
#95000
b1 b
b101 3
b101 D
b101 x
b0 (
b0 H
b0 r
b1 c
b101 5
b101 M
b101 4
b101 w
b1111 '
b1111 s
b0 d
b0 %
b0 u
b0 }
b0 8
b0 C
b0 F
1$
b0 7
b0 I
b0 _
b0 {
0#
b1111111111110101 /
b1111111111110101 z
b0 )
b0 E
b0 `
b0 q
1>
b0 B
b0 G
b0 ^
0@
b10101 g
b111111110101 1
b111111110101 y
b1111 &
b1111 t
b110 -
b110 N
b110111111110101 2
b110111111110101 f
b10101 h
b0 +
b0 n
b0 o
b10100 i
b10110 :
b10110 L
b10110 l
b100000 6
b100000 K
b0 0
b0 m
b10110 *
b10110 J
b10100 ,
b10100 j
b10100 p
1!
#100000
0!
#105000
b110 b
b110 c
b101 d
b101 %
b101 u
b101 }
b0 '
b0 s
0$
b101 7
b101 I
b101 _
b101 {
b101 8
b101 C
b101 F
b100000101 /
b100000101 z
b11000 )
b11000 E
b11000 `
b11000 q
1A
19
0>
b1 g
b100000101 1
b100000101 y
b1 &
b1 t
b11 -
b11 N
b11000100000101 2
b11000100000101 f
b1 h
b0 i
b10 +
b10 n
b10 o
b10 :
b10 L
b10 l
b1100 6
b1100 K
b1000001100 0
b1000001100 m
b10 *
b10 J
b0 ,
b0 j
b0 p
1!
#110000
0!
#115000
b100 b
b100 c
b11 d
b11 %
b11 u
b11 }
b11 7
b11 I
b11 _
b11 {
b11 8
b11 C
b11 F
1A
19
b11 3
b11 D
b11 x
b11 5
b11 M
b11 4
b11 w
b1000000011 /
b1000000011 z
b11 g
b1000000011 1
b1000000011 y
b10 &
b10 t
b11001000000011 2
b11001000000011 f
b11 h
b100 +
b100 n
b100 o
b10 i
b100 :
b100 L
b100 l
b11 )
b11 E
b11 `
b11 q
b1010 6
b1010 K
b10000001010 0
b10000001010 m
b100 *
b100 J
b10 ,
b10 j
b10 p
1!
#120000
0!
#125000
b1001 b
b0 3
b0 D
b0 x
b11 (
b11 H
b11 r
b1001 c
b0 5
b0 M
b0 4
b0 w
b10 '
b10 s
b1000 d
b1000 %
b1000 u
b1000 }
0$
b1000 7
b1000 I
b1000 _
b1000 {
b101 8
b101 C
b101 F
b100100000 /
b100100000 z
b101 )
b101 E
b101 `
b101 q
b0 B
b0 G
b0 ^
0A
19
b101 g
b100100000 1
b100100000 y
b1 &
b1 t
b0 -
b0 N
b100100000 2
b100100000 f
b101 h
b110 +
b110 n
b110 o
b100 i
b110 :
b110 L
b110 l
b110 6
b110 K
b1001000110 0
b1001000110 m
b110 *
b110 J
b100 ,
b100 j
b100 p
1!
#130000
0!
#135000
b1 B
b1 G
b1 ^
19
b100100001 /
b100100001 z
b1 3
b1 D
b1 x
b1 5
b1 M
b100100001 1
b100100001 y
b1 4
b1 w
b11111100 b
b100100001 2
b100100001 f
b11111100 c
b111 g
b11111011 d
b1111111111111011 %
b1111111111111011 u
b1111111111111011 }
b1111111111111011 7
b1111111111111011 I
b1111111111111011 _
b1111111111111011 {
b111 h
b1000 +
b1000 n
b1000 o
b1000 8
b1000 C
b1000 F
b110 i
b1000 :
b1000 L
b1000 l
b1000 )
b1000 E
b1000 `
b1000 q
b1010 6
b1010 K
b1001001010 0
b1001001010 m
b1000 *
b1000 J
b110 ,
b110 j
b110 p
1!
#140000
0!
#145000
b11 B
b11 G
b11 ^
19
b100100011 /
b100100011 z
b11 3
b11 D
b11 x
b11 5
b11 M
b100100011 1
b100100011 y
b11 4
b11 w
b100 b
b100100011 2
b100100011 f
b100 c
b1001 g
b11 d
b11 %
b11 u
b11 }
b11 7
b11 I
b11 _
b11 {
b1001 h
b1010 +
b1010 n
b1010 o
b1111111111111011 8
b1111111111111011 C
b1111111111111011 F
b1000 i
b1010 :
b1010 L
b1010 l
b1111111111111011 )
b1111111111111011 E
b1111111111111011 `
b1111111111111011 q
b10000 6
b10000 K
b1001010000 0
b1001010000 m
b1010 *
b1010 J
b1000 ,
b1000 j
b1000 p
1!
#150000
0!
#155000
b11001 b
b11001 c
b11000 d
b11000 %
b11000 u
b11000 }
b11000 7
b11000 I
b11000 _
b11000 {
b10 B
b10 G
b10 ^
19
b100100010 /
b100100010 z
b10 3
b10 D
b10 x
b10 5
b10 M
b100100010 1
b100100010 y
b10 4
b10 w
b100100010 2
b100100010 f
b1011 g
b1011 h
b1100 +
b1100 n
b1100 o
b11 8
b11 C
b11 F
b1010 i
b1100 :
b1100 L
b1100 l
b11 )
b11 E
b11 `
b11 q
b10000 6
b10000 K
b1001010000 0
b1001010000 m
b1100 *
b1100 J
b1010 ,
b1010 j
b1010 p
1!
#160000
0!
#165000
1$
b100000000 /
b100000000 z
b0 3
b0 D
b0 x
b0 (
b0 H
b0 r
b0 5
b0 M
b100000000 1
b100000000 y
b0 4
b0 w
b0 '
b0 s
b1 b
1;
1A
b0 B
b0 G
b0 ^
09
b1 c
b1101 g
b10 -
b10 N
b0 d
b0 %
b0 u
b0 }
b10000100000000 2
b10000100000000 f
b0 7
b0 I
b0 _
b0 {
b1101 h
b1110 +
b1110 n
b1110 o
b0 8
b0 C
b0 F
b1100 i
b1110 :
b1110 L
b1110 l
b11000 )
b11000 E
b11000 `
b11000 q
b1110 6
b1110 K
b1000001110 0
b1000001110 m
b1110 *
b1110 J
b1100 ,
b1100 j
b1100 p
1!
#170000
0!
